notata/__init__.py
notata/experiment.py
notata/logbook.py
notata/reader.py
notata-0.2.1.dist-info/licenses/LICENSE
notata-0.2.1.dist-info/METADATA
notata-0.2.1.dist-info/WHEEL
notata-0.2.1.dist-info/top_level.txt
notata-0.2.1.dist-info/RECORD
